awscli_plugin_eucalyptus/__init__.py
awscli_plugin_eucalyptus-0.3.dist-info/LICENSE
awscli_plugin_eucalyptus-0.3.dist-info/METADATA
awscli_plugin_eucalyptus-0.3.dist-info/WHEEL
awscli_plugin_eucalyptus-0.3.dist-info/top_level.txt
awscli_plugin_eucalyptus-0.3.dist-info/RECORD
