Metadata-Version: 2.1
Name: awscli-plugin-eucalyptus
Version: 0.3
Summary: Eucalyptus plugin for AWS CLI
Home-page: https://github.com/corymbia/eucalyptus-awscli-plugin
Author: Steve Jones
Author-email: steve@iaascream.cloud
License: BSD (Simplified)
Keywords: awscli,eucalyptus
Platform: UNKNOWN
Classifier: Development Status :: 4 - Beta
Classifier: License :: OSI Approved :: BSD License
Classifier: Operating System :: OS Independent
Classifier: Programming Language :: Python
Classifier: Programming Language :: Python :: 2
Classifier: Programming Language :: Python :: 2.7
Classifier: Programming Language :: Python :: 3
Classifier: Programming Language :: Python :: 3.9
Classifier: Topic :: Internet
Requires-Dist: awscli (>=1.11.0)
